hole_filling/__init__.py
hole_filling/hole_filling.py
hole_filling-1.0.0.dist-info/LICENSE
hole_filling-1.0.0.dist-info/METADATA
hole_filling-1.0.0.dist-info/WHEEL
hole_filling-1.0.0.dist-info/top_level.txt
hole_filling-1.0.0.dist-info/RECORD
