Metadata-Version: 2.1
Name: hole-filling
Version: 1.0.0
Summary: A simple Python package for hole filling in triangle meshes.
Home-page: https://github.com/kentechx/hole-filling
Author: Kaidi Shen
License: UNKNOWN
Platform: UNKNOWN
Classifier: Programming Language :: Python :: 3
Classifier: License :: OSI Approved :: MIT License
License-File: LICENSE
Requires-Dist: libigl
Requires-Dist: scipy
